[
  {
    "City": "Abbyville",
    "Zip Codes": [
      67510
    ]
  },
  {
    "City": "Abilene",
    "Zip Codes": [
      67410
    ]
  },
  {
    "City": "Admire",
    "Zip Codes": [
      66830
    ]
  },
  {
    "City": "Agenda",
    "Zip Codes": [
      66930
    ]
  },
  {
    "City": "Agra",
    "Zip Codes": [
      67621
    ]
  },
  {
    "City": "Albert",
    "Zip Codes": [
      67511
    ]
  },
  {
    "City": "Alden",
    "Zip Codes": [
      67512
    ]
  },
  {
    "City": "Alexander",
    "Zip Codes": [
      67513
    ]
  },
  {
    "City": "Allen",
    "Zip Codes": [
      66833
    ]
  },
  {
    "City": "Alma",
    "Zip Codes": [
      66401
    ]
  },
  {
    "City": "Almena",
    "Zip Codes": [
      67622
    ]
  },
  {
    "City": "Alta Vista",
    "Zip Codes": [
      66834
    ]
  },
  {
    "City": "Altamont",
    "Zip Codes": [
      67330
    ]
  },
  {
    "City": "Alton",
    "Zip Codes": [
      67623
    ]
  },
  {
    "City": "Altoona",
    "Zip Codes": [
      66710
    ]
  },
  {
    "City": "Americus",
    "Zip Codes": [
      66835
    ]
  },
  {
    "City": "Andale",
    "Zip Codes": [
      67001
    ]
  },
  {
    "City": "Andover",
    "Zip Codes": [
      67002
    ]
  },
  {
    "City": "Anthony",
    "Zip Codes": [
      67003
    ]
  },
  {
    "City": "Arcadia",
    "Zip Codes": [
      66711
    ]
  },
  {
    "City": "Argonia",
    "Zip Codes": [
      67004
    ]
  },
  {
    "City": "Arkansas City",
    "Zip Codes": [
      67005
    ]
  },
  {
    "City": "Arlington",
    "Zip Codes": [
      67514
    ]
  },
  {
    "City": "Arma",
    "Zip Codes": [
      66712
    ]
  },
  {
    "City": "Arnold",
    "Zip Codes": [
      67515
    ]
  },
  {
    "City": "Ashland",
    "Zip Codes": [
      67831
    ]
  },
  {
    "City": "Assaria",
    "Zip Codes": [
      67416
    ]
  },
  {
    "City": "Atchison",
    "Zip Codes": [
      66002
    ]
  },
  {
    "City": "Athol",
    "Zip Codes": [
      66932
    ]
  },
  {
    "City": "Atlanta",
    "Zip Codes": [
      67008
    ]
  },
  {
    "City": "Attica",
    "Zip Codes": [
      67009
    ]
  },
  {
    "City": "Atwood",
    "Zip Codes": [
      67730
    ]
  },
  {
    "City": "Auburn",
    "Zip Codes": [
      66402
    ]
  },
  {
    "City": "Augusta",
    "Zip Codes": [
      67010
    ]
  },
  {
    "City": "Aurora",
    "Zip Codes": [
      67417
    ]
  },
  {
    "City": "Axtell",
    "Zip Codes": [
      66403
    ]
  },
  {
    "City": "Baileyville",
    "Zip Codes": [
      66404
    ]
  },
  {
    "City": "Baldwin City",
    "Zip Codes": [
      66006
    ]
  },
  {
    "City": "Barnard",
    "Zip Codes": [
      67418
    ]
  },
  {
    "City": "Barnes",
    "Zip Codes": [
      66933
    ]
  },
  {
    "City": "Bartlett",
    "Zip Codes": [
      67332
    ]
  },
  {
    "City": "Basehor",
    "Zip Codes": [
      66007
    ]
  },
  {
    "City": "Baxter Springs",
    "Zip Codes": [
      66713
    ]
  },
  {
    "City": "Bazine",
    "Zip Codes": [
      67516
    ]
  },
  {
    "City": "Beattie",
    "Zip Codes": [
      66406
    ]
  },
  {
    "City": "Beaumont",
    "Zip Codes": [
      67012
    ]
  },
  {
    "City": "Beeler",
    "Zip Codes": [
      67518
    ]
  },
  {
    "City": "Belle Plaine",
    "Zip Codes": [
      67013
    ]
  },
  {
    "City": "Belleville",
    "Zip Codes": [
      66935
    ]
  },
  {
    "City": "Beloit",
    "Zip Codes": [
      67420
    ]
  },
  {
    "City": "Belpre",
    "Zip Codes": [
      67519
    ]
  },
  {
    "City": "Belvue",
    "Zip Codes": [
      66407
    ]
  },
  {
    "City": "Bendena",
    "Zip Codes": [
      66008
    ]
  },
  {
    "City": "Benedict",
    "Zip Codes": [
      66714
    ]
  },
  {
    "City": "Bennington",
    "Zip Codes": [
      67422
    ]
  },
  {
    "City": "Bentley",
    "Zip Codes": [
      67016
    ]
  },
  {
    "City": "Benton",
    "Zip Codes": [
      67017
    ]
  },
  {
    "City": "Bern",
    "Zip Codes": [
      66408
    ]
  },
  {
    "City": "Berryton",
    "Zip Codes": [
      66409
    ]
  },
  {
    "City": "Beverly",
    "Zip Codes": [
      67423
    ]
  },
  {
    "City": "Bird City",
    "Zip Codes": [
      67731
    ]
  },
  {
    "City": "Bison",
    "Zip Codes": [
      67520
    ]
  },
  {
    "City": "Blue Mound",
    "Zip Codes": [
      66010
    ]
  },
  {
    "City": "Blue Rapids",
    "Zip Codes": [
      66411
    ]
  },
  {
    "City": "Bluff City",
    "Zip Codes": [
      67018
    ]
  },
  {
    "City": "Bogue",
    "Zip Codes": [
      67625
    ]
  },
  {
    "City": "Bonner Springs",
    "Zip Codes": [
      66012
    ]
  },
  {
    "City": "Bremen",
    "Zip Codes": [
      66412
    ]
  },
  {
    "City": "Brewster",
    "Zip Codes": [
      67732
    ]
  },
  {
    "City": "Bronson",
    "Zip Codes": [
      66716
    ]
  },
  {
    "City": "Brookville",
    "Zip Codes": [
      67425
    ]
  },
  {
    "City": "Brownell",
    "Zip Codes": [
      67521
    ]
  },
  {
    "City": "Bucklin",
    "Zip Codes": [
      67834
    ]
  },
  {
    "City": "Bucyrus",
    "Zip Codes": [
      66013
    ]
  },
  {
    "City": "Buffalo",
    "Zip Codes": [
      66717
    ]
  },
  {
    "City": "Buhler",
    "Zip Codes": [
      67522
    ]
  },
  {
    "City": "Bunker Hill",
    "Zip Codes": [
      67626
    ]
  },
  {
    "City": "Burden",
    "Zip Codes": [
      67019
    ]
  },
  {
    "City": "Burdett",
    "Zip Codes": [
      67523
    ]
  },
  {
    "City": "Burdick",
    "Zip Codes": [
      66838
    ]
  },
  {
    "City": "Burlingame",
    "Zip Codes": [
      66413
    ]
  },
  {
    "City": "Burlington",
    "Zip Codes": [
      66839
    ]
  },
  {
    "City": "Burns",
    "Zip Codes": [
      66840
    ]
  },
  {
    "City": "Burr Oak",
    "Zip Codes": [
      66936
    ]
  },
  {
    "City": "Burrton",
    "Zip Codes": [
      67020
    ]
  },
  {
    "City": "Bushton",
    "Zip Codes": [
      67427
    ]
  },
  {
    "City": "Byers",
    "Zip Codes": [
      67021
    ]
  },
  {
    "City": "Caldwell",
    "Zip Codes": [
      67022
    ]
  },
  {
    "City": "Cambridge",
    "Zip Codes": [
      67023
    ]
  },
  {
    "City": "Caney",
    "Zip Codes": [
      67333
    ]
  },
  {
    "City": "Canton",
    "Zip Codes": [
      67428
    ]
  },
  {
    "City": "Carbondale",
    "Zip Codes": [
      66414
    ]
  },
  {
    "City": "Cassoday",
    "Zip Codes": [
      66842
    ]
  },
  {
    "City": "Cawker City",
    "Zip Codes": [
      67430
    ]
  },
  {
    "City": "Cedar",
    "Zip Codes": [
      67628
    ]
  },
  {
    "City": "Cedar Point",
    "Zip Codes": [
      66843
    ]
  },
  {
    "City": "Cedar Vale",
    "Zip Codes": [
      67024
    ]
  },
  {
    "City": "Centerville",
    "Zip Codes": [
      66014
    ]
  },
  {
    "City": "Centralia",
    "Zip Codes": [
      66415
    ]
  },
  {
    "City": "Chanute",
    "Zip Codes": [
      66720
    ]
  },
  {
    "City": "Chapman",
    "Zip Codes": [
      67431
    ]
  },
  {
    "City": "Chase",
    "Zip Codes": [
      67524
    ]
  },
  {
    "City": "Chautauqua",
    "Zip Codes": [
      67334
    ]
  },
  {
    "City": "Cheney",
    "Zip Codes": [
      67025
    ]
  },
  {
    "City": "Cherokee",
    "Zip Codes": [
      66724
    ]
  },
  {
    "City": "Cherryvale",
    "Zip Codes": [
      67335
    ]
  },
  {
    "City": "Chetopa",
    "Zip Codes": [
      67336
    ]
  },
  {
    "City": "Cimarron",
    "Zip Codes": [
      67835
    ]
  },
  {
    "City": "Circleville",
    "Zip Codes": [
      66416
    ]
  },
  {
    "City": "Claflin",
    "Zip Codes": [
      67525
    ]
  },
  {
    "City": "Clay Center",
    "Zip Codes": [
      67432
    ]
  },
  {
    "City": "Clayton",
    "Zip Codes": [
      67629
    ]
  },
  {
    "City": "Clearwater",
    "Zip Codes": [
      67026
    ]
  },
  {
    "City": "Clifton",
    "Zip Codes": [
      66937
    ]
  },
  {
    "City": "Clyde",
    "Zip Codes": [
      66938
    ]
  },
  {
    "City": "Coats",
    "Zip Codes": [
      67028
    ]
  },
  {
    "City": "Coffeyville",
    "Zip Codes": [
      67337
    ]
  },
  {
    "City": "Colby",
    "Zip Codes": [
      67701
    ]
  },
  {
    "City": "Coldwater",
    "Zip Codes": [
      67029
    ]
  },
  {
    "City": "Collyer",
    "Zip Codes": [
      67631
    ]
  },
  {
    "City": "Colony",
    "Zip Codes": [
      66015
    ]
  },
  {
    "City": "Columbus",
    "Zip Codes": [
      66725
    ]
  },
  {
    "City": "Colwich",
    "Zip Codes": [
      67030
    ]
  },
  {
    "City": "Concordia",
    "Zip Codes": [
      66901
    ]
  },
  {
    "City": "Conway Springs",
    "Zip Codes": [
      67031
    ]
  },
  {
    "City": "Coolidge",
    "Zip Codes": [
      67836
    ]
  },
  {
    "City": "Copeland",
    "Zip Codes": [
      67837
    ]
  },
  {
    "City": "Corning",
    "Zip Codes": [
      66417
    ]
  },
  {
    "City": "Cottonwood Falls",
    "Zip Codes": [
      66845
    ]
  },
  {
    "City": "Council Grove",
    "Zip Codes": [
      66846
    ]
  },
  {
    "City": "Courtland",
    "Zip Codes": [
      66939
    ]
  },
  {
    "City": "Crestline",
    "Zip Codes": [
      66728
    ]
  },
  {
    "City": "Cuba",
    "Zip Codes": [
      66940
    ]
  },
  {
    "City": "Cummings",
    "Zip Codes": [
      66016
    ]
  },
  {
    "City": "Cunningham",
    "Zip Codes": [
      67035
    ]
  },
  {
    "City": "Damar",
    "Zip Codes": [
      67632
    ]
  },
  {
    "City": "Danville",
    "Zip Codes": [
      67036
    ]
  },
  {
    "City": "De Soto",
    "Zip Codes": [
      66018
    ]
  },
  {
    "City": "Dearing",
    "Zip Codes": [
      67340
    ]
  },
  {
    "City": "Deerfield",
    "Zip Codes": [
      67838
    ]
  },
  {
    "City": "Delia",
    "Zip Codes": [
      66418
    ]
  },
  {
    "City": "Delphos",
    "Zip Codes": [
      67436
    ]
  },
  {
    "City": "Denison",
    "Zip Codes": [
      66419
    ]
  },
  {
    "City": "Dennis",
    "Zip Codes": [
      67341
    ]
  },
  {
    "City": "Denton",
    "Zip Codes": [
      66017
    ]
  },
  {
    "City": "Derby",
    "Zip Codes": [
      67037
    ]
  },
  {
    "City": "Dexter",
    "Zip Codes": [
      67038
    ]
  },
  {
    "City": "Dighton",
    "Zip Codes": [
      67839
    ]
  },
  {
    "City": "Dodge City",
    "Zip Codes": [
      67801
    ]
  },
  {
    "City": "Dorrance",
    "Zip Codes": [
      67634
    ]
  },
  {
    "City": "Douglass",
    "Zip Codes": [
      67039
    ]
  },
  {
    "City": "Downs",
    "Zip Codes": [
      67437
    ]
  },
  {
    "City": "Dresden",
    "Zip Codes": [
      67635
    ]
  },
  {
    "City": "Durham",
    "Zip Codes": [
      67438
    ]
  },
  {
    "City": "Dwight",
    "Zip Codes": [
      66849
    ]
  },
  {
    "City": "Easton",
    "Zip Codes": [
      66020
    ]
  },
  {
    "City": "Edgerton",
    "Zip Codes": [
      66021
    ]
  },
  {
    "City": "Edna",
    "Zip Codes": [
      67342
    ]
  },
  {
    "City": "Edson",
    "Zip Codes": [
      67733
    ]
  },
  {
    "City": "Effingham",
    "Zip Codes": [
      66023
    ]
  },
  {
    "City": "El Dorado",
    "Zip Codes": [
      67042
    ]
  },
  {
    "City": "Elbing",
    "Zip Codes": [
      67041
    ]
  },
  {
    "City": "Elk City",
    "Zip Codes": [
      67344
    ]
  },
  {
    "City": "Elk Falls",
    "Zip Codes": [
      67345
    ]
  },
  {
    "City": "Elkhart",
    "Zip Codes": [
      67950
    ]
  },
  {
    "City": "Ellinwood",
    "Zip Codes": [
      67526
    ]
  },
  {
    "City": "Ellis",
    "Zip Codes": [
      67637
    ]
  },
  {
    "City": "Ellsworth",
    "Zip Codes": [
      67439
    ]
  },
  {
    "City": "Elmdale",
    "Zip Codes": [
      66850
    ]
  },
  {
    "City": "Elsmore",
    "Zip Codes": [
      66732
    ]
  },
  {
    "City": "Elwood",
    "Zip Codes": [
      66024
    ]
  },
  {
    "City": "Emmett",
    "Zip Codes": [
      66422
    ]
  },
  {
    "City": "Emporia",
    "Zip Codes": [
      66801
    ]
  },
  {
    "City": "Englewood",
    "Zip Codes": [
      67840
    ]
  },
  {
    "City": "Ensign",
    "Zip Codes": [
      67841
    ]
  },
  {
    "City": "Enterprise",
    "Zip Codes": [
      67441
    ]
  },
  {
    "City": "Erie",
    "Zip Codes": [
      66733
    ]
  },
  {
    "City": "Esbon",
    "Zip Codes": [
      66941
    ]
  },
  {
    "City": "Eskridge",
    "Zip Codes": [
      66423
    ]
  },
  {
    "City": "Eudora",
    "Zip Codes": [
      66025
    ]
  },
  {
    "City": "Eureka",
    "Zip Codes": [
      67045
    ]
  },
  {
    "City": "Everest",
    "Zip Codes": [
      66424
    ]
  },
  {
    "City": "Fairview",
    "Zip Codes": [
      66425
    ]
  },
  {
    "City": "Fall River",
    "Zip Codes": [
      67047
    ]
  },
  {
    "City": "Falun",
    "Zip Codes": [
      67442
    ]
  },
  {
    "City": "Farlington",
    "Zip Codes": [
      66734
    ]
  },
  {
    "City": "Florence",
    "Zip Codes": [
      66851
    ]
  },
  {
    "City": "Fontana",
    "Zip Codes": [
      66026
    ]
  },
  {
    "City": "Ford",
    "Zip Codes": [
      67842
    ]
  },
  {
    "City": "Formoso",
    "Zip Codes": [
      66942
    ]
  },
  {
    "City": "Fort Dodge",
    "Zip Codes": [
      67843
    ]
  },
  {
    "City": "Fort Leavenworth",
    "Zip Codes": [
      66027
    ]
  },
  {
    "City": "Fort Riley",
    "Zip Codes": [
      66442
    ]
  },
  {
    "City": "Fort Scott",
    "Zip Codes": [
      66701
    ]
  },
  {
    "City": "Fowler",
    "Zip Codes": [
      67844
    ]
  },
  {
    "City": "Frankfort",
    "Zip Codes": [
      66427
    ]
  },
  {
    "City": "Franklin",
    "Zip Codes": [
      66735
    ]
  },
  {
    "City": "Fredonia",
    "Zip Codes": [
      66736
    ]
  },
  {
    "City": "Freeport",
    "Zip Codes": [
      67049
    ]
  },
  {
    "City": "Frontenac",
    "Zip Codes": [
      66763
    ]
  },
  {
    "City": "Fulton",
    "Zip Codes": [
      66738
    ]
  },
  {
    "City": "Galena",
    "Zip Codes": [
      66739
    ]
  },
  {
    "City": "Galesburg",
    "Zip Codes": [
      66740
    ]
  },
  {
    "City": "Galva",
    "Zip Codes": [
      67443
    ]
  },
  {
    "City": "Garden City",
    "Zip Codes": [
      67846
    ]
  },
  {
    "City": "Garden Plain",
    "Zip Codes": [
      67050
    ]
  },
  {
    "City": "Gardner",
    "Zip Codes": [
      66030
    ]
  },
  {
    "City": "Garfield",
    "Zip Codes": [
      67529
    ]
  },
  {
    "City": "Garland",
    "Zip Codes": [
      66741
    ]
  },
  {
    "City": "Garnett",
    "Zip Codes": [
      66032
    ]
  },
  {
    "City": "Gaylord",
    "Zip Codes": [
      67638
    ]
  },
  {
    "City": "Gem",
    "Zip Codes": [
      67734
    ]
  },
  {
    "City": "Geneseo",
    "Zip Codes": [
      67444
    ]
  },
  {
    "City": "Geuda Springs",
    "Zip Codes": [
      67051
    ]
  },
  {
    "City": "Girard",
    "Zip Codes": [
      66743
    ]
  },
  {
    "City": "Glade",
    "Zip Codes": [
      67639
    ]
  },
  {
    "City": "Glasco",
    "Zip Codes": [
      67445
    ]
  },
  {
    "City": "Glen Elder",
    "Zip Codes": [
      67446
    ]
  },
  {
    "City": "Goddard",
    "Zip Codes": [
      67052
    ]
  },
  {
    "City": "Goessel",
    "Zip Codes": [
      67053
    ]
  },
  {
    "City": "Goff",
    "Zip Codes": [
      66428
    ]
  },
  {
    "City": "Goodland",
    "Zip Codes": [
      67735
    ]
  },
  {
    "City": "Gorham",
    "Zip Codes": [
      67640
    ]
  },
  {
    "City": "Gove",
    "Zip Codes": [
      67736
    ]
  },
  {
    "City": "Grainfield",
    "Zip Codes": [
      67737
    ]
  },
  {
    "City": "Grantville",
    "Zip Codes": [
      66429
    ]
  },
  {
    "City": "Great Bend",
    "Zip Codes": [
      67530
    ]
  },
  {
    "City": "Greeley",
    "Zip Codes": [
      66033
    ]
  },
  {
    "City": "Green",
    "Zip Codes": [
      67447
    ]
  },
  {
    "City": "Greenleaf",
    "Zip Codes": [
      66943
    ]
  },
  {
    "City": "Greensburg",
    "Zip Codes": [
      67054
    ]
  },
  {
    "City": "Greenwich",
    "Zip Codes": [
      67055
    ]
  },
  {
    "City": "Grenola",
    "Zip Codes": [
      67346
    ]
  },
  {
    "City": "Gridley",
    "Zip Codes": [
      66852
    ]
  },
  {
    "City": "Grinnell",
    "Zip Codes": [
      67738
    ]
  },
  {
    "City": "Gypsum",
    "Zip Codes": [
      67448
    ]
  },
  {
    "City": "Haddam",
    "Zip Codes": [
      66944
    ]
  },
  {
    "City": "Halstead",
    "Zip Codes": [
      67056
    ]
  },
  {
    "City": "Hamilton",
    "Zip Codes": [
      66853
    ]
  },
  {
    "City": "Hanover",
    "Zip Codes": [
      66945
    ]
  },
  {
    "City": "Hanston",
    "Zip Codes": [
      67849
    ]
  },
  {
    "City": "Hardtner",
    "Zip Codes": [
      67057
    ]
  },
  {
    "City": "Harper",
    "Zip Codes": [
      67058
    ]
  },
  {
    "City": "Hartford",
    "Zip Codes": [
      66854
    ]
  },
  {
    "City": "Harveyville",
    "Zip Codes": [
      66431
    ]
  },
  {
    "City": "Havana",
    "Zip Codes": [
      67347
    ]
  },
  {
    "City": "Haven",
    "Zip Codes": [
      67543
    ]
  },
  {
    "City": "Havensville",
    "Zip Codes": [
      66432
    ]
  },
  {
    "City": "Haviland",
    "Zip Codes": [
      67059
    ]
  },
  {
    "City": "Hays",
    "Zip Codes": [
      67601
    ]
  },
  {
    "City": "Haysville",
    "Zip Codes": [
      67060
    ]
  },
  {
    "City": "Hazelton",
    "Zip Codes": [
      67061
    ]
  },
  {
    "City": "Healy",
    "Zip Codes": [
      67850
    ]
  },
  {
    "City": "Hepler",
    "Zip Codes": [
      66746
    ]
  },
  {
    "City": "Herington",
    "Zip Codes": [
      67449
    ]
  },
  {
    "City": "Herndon",
    "Zip Codes": [
      67739
    ]
  },
  {
    "City": "Hesston",
    "Zip Codes": [
      67062
    ]
  },
  {
    "City": "Hiawatha",
    "Zip Codes": [
      66434
    ]
  },
  {
    "City": "Highland",
    "Zip Codes": [
      66035
    ]
  },
  {
    "City": "Hill City",
    "Zip Codes": [
      67642
    ]
  },
  {
    "City": "Hillsboro",
    "Zip Codes": [
      67063
    ]
  },
  {
    "City": "Hoisington",
    "Zip Codes": [
      67544
    ]
  },
  {
    "City": "Holcomb",
    "Zip Codes": [
      67851
    ]
  },
  {
    "City": "Hollenberg",
    "Zip Codes": [
      66946
    ]
  },
  {
    "City": "Holton",
    "Zip Codes": [
      66436
    ]
  },
  {
    "City": "Holyrood",
    "Zip Codes": [
      67450
    ]
  },
  {
    "City": "Home",
    "Zip Codes": [
      66438
    ]
  },
  {
    "City": "Hope",
    "Zip Codes": [
      67451
    ]
  },
  {
    "City": "Horton",
    "Zip Codes": [
      66439
    ]
  },
  {
    "City": "Howard",
    "Zip Codes": [
      67349
    ]
  },
  {
    "City": "Hoxie",
    "Zip Codes": [
      67740
    ]
  },
  {
    "City": "Hoyt",
    "Zip Codes": [
      66440
    ]
  },
  {
    "City": "Hudson",
    "Zip Codes": [
      67545
    ]
  },
  {
    "City": "Hugoton",
    "Zip Codes": [
      67951
    ]
  },
  {
    "City": "Humboldt",
    "Zip Codes": [
      66748
    ]
  },
  {
    "City": "Hunter",
    "Zip Codes": [
      67452
    ]
  },
  {
    "City": "Hutchinson",
    "Zip Codes": [
      67501,
      67502
    ]
  },
  {
    "City": "Independence",
    "Zip Codes": [
      67301
    ]
  },
  {
    "City": "Ingalls",
    "Zip Codes": [
      67853
    ]
  },
  {
    "City": "Inman",
    "Zip Codes": [
      67546
    ]
  },
  {
    "City": "Iola",
    "Zip Codes": [
      66749
    ]
  },
  {
    "City": "Isabel",
    "Zip Codes": [
      67065
    ]
  },
  {
    "City": "Iuka",
    "Zip Codes": [
      67066
    ]
  },
  {
    "City": "Jamestown",
    "Zip Codes": [
      66948
    ]
  },
  {
    "City": "Jennings",
    "Zip Codes": [
      67643
    ]
  },
  {
    "City": "Jetmore",
    "Zip Codes": [
      67854
    ]
  },
  {
    "City": "Jewell",
    "Zip Codes": [
      66949
    ]
  },
  {
    "City": "Johnson",
    "Zip Codes": [
      67855
    ]
  },
  {
    "City": "Junction City",
    "Zip Codes": [
      66441
    ]
  },
  {
    "City": "Kanopolis",
    "Zip Codes": [
      67454
    ]
  },
  {
    "City": "Kanorado",
    "Zip Codes": [
      67741
    ]
  },
  {
    "City": "Kansas City",
    "Zip Codes": [
      66109,
      66101,
      66104,
      66106,
      66102,
      66103,
      66111,
      66105,
      66115,
      66118,
      66112
    ]
  },
  {
    "City": "Kechi",
    "Zip Codes": [
      67067
    ]
  },
  {
    "City": "Kendall",
    "Zip Codes": [
      67857
    ]
  },
  {
    "City": "Kensington",
    "Zip Codes": [
      66951
    ]
  },
  {
    "City": "Kincaid",
    "Zip Codes": [
      66039
    ]
  },
  {
    "City": "Kingman",
    "Zip Codes": [
      67068
    ]
  },
  {
    "City": "Kinsley",
    "Zip Codes": [
      67547
    ]
  },
  {
    "City": "Kiowa",
    "Zip Codes": [
      67070
    ]
  },
  {
    "City": "Kirwin",
    "Zip Codes": [
      67644
    ]
  },
  {
    "City": "Kismet",
    "Zip Codes": [
      67859
    ]
  },
  {
    "City": "La Crosse",
    "Zip Codes": [
      67548
    ]
  },
  {
    "City": "La Cygne",
    "Zip Codes": [
      66040
    ]
  },
  {
    "City": "La Harpe",
    "Zip Codes": [
      66751
    ]
  },
  {
    "City": "Lake City",
    "Zip Codes": [
      67071
    ]
  },
  {
    "City": "Lakin",
    "Zip Codes": [
      67860
    ]
  },
  {
    "City": "Lancaster",
    "Zip Codes": [
      66041
    ]
  },
  {
    "City": "Lane",
    "Zip Codes": [
      66042
    ]
  },
  {
    "City": "Lansing",
    "Zip Codes": [
      66043
    ]
  },
  {
    "City": "Larned",
    "Zip Codes": [
      67550
    ]
  },
  {
    "City": "Latham",
    "Zip Codes": [
      67072
    ]
  },
  {
    "City": "Lawrence",
    "Zip Codes": [
      66049,
      66044,
      66045,
      66047,
      66046
    ]
  },
  {
    "City": "Le Roy",
    "Zip Codes": [
      66857
    ]
  },
  {
    "City": "Leavenworth",
    "Zip Codes": [
      66048
    ]
  },
  {
    "City": "Leawood",
    "Zip Codes": [
      66209,
      66211,
      66206
    ]
  },
  {
    "City": "Lebanon",
    "Zip Codes": [
      66952
    ]
  },
  {
    "City": "Lebo",
    "Zip Codes": [
      66856
    ]
  },
  {
    "City": "Lecompton",
    "Zip Codes": [
      66050
    ]
  },
  {
    "City": "Lehigh",
    "Zip Codes": [
      67073
    ]
  },
  {
    "City": "Lenexa",
    "Zip Codes": [
      66220,
      66219,
      66227,
      66215
    ]
  },
  {
    "City": "Lenora",
    "Zip Codes": [
      67645
    ]
  },
  {
    "City": "Leon",
    "Zip Codes": [
      67074
    ]
  },
  {
    "City": "Leonardville",
    "Zip Codes": [
      66449
    ]
  },
  {
    "City": "Leoti",
    "Zip Codes": [
      67861
    ]
  },
  {
    "City": "Levant",
    "Zip Codes": [
      67743
    ]
  },
  {
    "City": "Lewis",
    "Zip Codes": [
      67552
    ]
  },
  {
    "City": "Liberal",
    "Zip Codes": [
      67901
    ]
  },
  {
    "City": "Liberty",
    "Zip Codes": [
      67351
    ]
  },
  {
    "City": "Liebenthal",
    "Zip Codes": [
      67553
    ]
  },
  {
    "City": "Lincoln",
    "Zip Codes": [
      67455
    ]
  },
  {
    "City": "Lincolnville",
    "Zip Codes": [
      66858
    ]
  },
  {
    "City": "Lindsborg",
    "Zip Codes": [
      67456
    ]
  },
  {
    "City": "Linn",
    "Zip Codes": [
      66953
    ]
  },
  {
    "City": "Linwood",
    "Zip Codes": [
      66052
    ]
  },
  {
    "City": "Little River",
    "Zip Codes": [
      67457
    ]
  },
  {
    "City": "Logan",
    "Zip Codes": [
      67646
    ]
  },
  {
    "City": "Long Island",
    "Zip Codes": [
      67647
    ]
  },
  {
    "City": "Longford",
    "Zip Codes": [
      67458
    ]
  },
  {
    "City": "Longton",
    "Zip Codes": [
      67352
    ]
  },
  {
    "City": "Lorraine",
    "Zip Codes": [
      67459
    ]
  },
  {
    "City": "Lost Springs",
    "Zip Codes": [
      66859
    ]
  },
  {
    "City": "Louisburg",
    "Zip Codes": [
      66053
    ]
  },
  {
    "City": "Lucas",
    "Zip Codes": [
      67648
    ]
  },
  {
    "City": "Ludell",
    "Zip Codes": [
      67744
    ]
  },
  {
    "City": "Luray",
    "Zip Codes": [
      67649
    ]
  },
  {
    "City": "Lyndon",
    "Zip Codes": [
      66451
    ]
  },
  {
    "City": "Lyons",
    "Zip Codes": [
      67554
    ]
  },
  {
    "City": "Macksville",
    "Zip Codes": [
      67557
    ]
  },
  {
    "City": "Madison",
    "Zip Codes": [
      66860
    ]
  },
  {
    "City": "Mahaska",
    "Zip Codes": [
      66955
    ]
  },
  {
    "City": "Maize",
    "Zip Codes": [
      67101
    ]
  },
  {
    "City": "Manhattan",
    "Zip Codes": [
      66506,
      66503,
      66502
    ]
  },
  {
    "City": "Mankato",
    "Zip Codes": [
      66956
    ]
  },
  {
    "City": "Manter",
    "Zip Codes": [
      67862
    ]
  },
  {
    "City": "Maple Hill",
    "Zip Codes": [
      66507
    ]
  },
  {
    "City": "Mapleton",
    "Zip Codes": [
      66754
    ]
  },
  {
    "City": "Marienthal",
    "Zip Codes": [
      67863
    ]
  },
  {
    "City": "Marion",
    "Zip Codes": [
      66861
    ]
  },
  {
    "City": "Marquette",
    "Zip Codes": [
      67464
    ]
  },
  {
    "City": "Marysville",
    "Zip Codes": [
      66508
    ]
  },
  {
    "City": "Matfield Green",
    "Zip Codes": [
      66862
    ]
  },
  {
    "City": "Mayetta",
    "Zip Codes": [
      66509
    ]
  },
  {
    "City": "Mayfield",
    "Zip Codes": [
      67103
    ]
  },
  {
    "City": "McCracken",
    "Zip Codes": [
      67556
    ]
  },
  {
    "City": "McCune",
    "Zip Codes": [
      66753
    ]
  },
  {
    "City": "McDonald",
    "Zip Codes": [
      67745
    ]
  },
  {
    "City": "McFarland",
    "Zip Codes": [
      66501
    ]
  },
  {
    "City": "McLouth",
    "Zip Codes": [
      66054
    ]
  },
  {
    "City": "Mcpherson",
    "Zip Codes": [
      67460
    ]
  },
  {
    "City": "Meade",
    "Zip Codes": [
      67864
    ]
  },
  {
    "City": "Medicine Lodge",
    "Zip Codes": [
      67104
    ]
  },
  {
    "City": "Melvern",
    "Zip Codes": [
      66510
    ]
  },
  {
    "City": "Meriden",
    "Zip Codes": [
      66512
    ]
  },
  {
    "City": "Milan",
    "Zip Codes": [
      67105
    ]
  },
  {
    "City": "Milford",
    "Zip Codes": [
      66514
    ]
  },
  {
    "City": "Milton",
    "Zip Codes": [
      67106
    ]
  },
  {
    "City": "Miltonvale",
    "Zip Codes": [
      67466
    ]
  },
  {
    "City": "Minneapolis",
    "Zip Codes": [
      67467
    ]
  },
  {
    "City": "Minneola",
    "Zip Codes": [
      67865
    ]
  },
  {
    "City": "Mission",
    "Zip Codes": [
      66205,
      66202
    ]
  },
  {
    "City": "Moline",
    "Zip Codes": [
      67353
    ]
  },
  {
    "City": "Montezuma",
    "Zip Codes": [
      67867
    ]
  },
  {
    "City": "Monument",
    "Zip Codes": [
      67747
    ]
  },
  {
    "City": "Moran",
    "Zip Codes": [
      66755
    ]
  },
  {
    "City": "Morganville",
    "Zip Codes": [
      67468
    ]
  },
  {
    "City": "Morland",
    "Zip Codes": [
      67650
    ]
  },
  {
    "City": "Morrill",
    "Zip Codes": [
      66515
    ]
  },
  {
    "City": "Morrowville",
    "Zip Codes": [
      66958
    ]
  },
  {
    "City": "Moscow",
    "Zip Codes": [
      67952
    ]
  },
  {
    "City": "Mound City",
    "Zip Codes": [
      66056
    ]
  },
  {
    "City": "Mound Valley",
    "Zip Codes": [
      67354
    ]
  },
  {
    "City": "Moundridge",
    "Zip Codes": [
      67107
    ]
  },
  {
    "City": "Mount Hope",
    "Zip Codes": [
      67108
    ]
  },
  {
    "City": "Mulberry",
    "Zip Codes": [
      66756
    ]
  },
  {
    "City": "Mullinville",
    "Zip Codes": [
      67109
    ]
  },
  {
    "City": "Mulvane",
    "Zip Codes": [
      67110
    ]
  },
  {
    "City": "Munden",
    "Zip Codes": [
      66959
    ]
  },
  {
    "City": "Murdock",
    "Zip Codes": [
      67111
    ]
  },
  {
    "City": "Muscotah",
    "Zip Codes": [
      66058
    ]
  },
  {
    "City": "Narka",
    "Zip Codes": [
      66960
    ]
  },
  {
    "City": "Nashville",
    "Zip Codes": [
      67112
    ]
  },
  {
    "City": "Natoma",
    "Zip Codes": [
      67651
    ]
  },
  {
    "City": "Neal",
    "Zip Codes": [
      66863
    ]
  },
  {
    "City": "Nekoma",
    "Zip Codes": [
      67559
    ]
  },
  {
    "City": "Neodesha",
    "Zip Codes": [
      66757
    ]
  },
  {
    "City": "Neosho Falls",
    "Zip Codes": [
      66758
    ]
  },
  {
    "City": "Neosho Rapids",
    "Zip Codes": [
      66864
    ]
  },
  {
    "City": "Ness City",
    "Zip Codes": [
      67560
    ]
  },
  {
    "City": "Netawaka",
    "Zip Codes": [
      66516
    ]
  },
  {
    "City": "New Cambria",
    "Zip Codes": [
      67470
    ]
  },
  {
    "City": "New Century",
    "Zip Codes": [
      66031
    ]
  },
  {
    "City": "Newton",
    "Zip Codes": [
      67114
    ]
  },
  {
    "City": "Nickerson",
    "Zip Codes": [
      67561
    ]
  },
  {
    "City": "Niotaze",
    "Zip Codes": [
      67355
    ]
  },
  {
    "City": "Norcatur",
    "Zip Codes": [
      67653
    ]
  },
  {
    "City": "North Newton",
    "Zip Codes": [
      67117
    ]
  },
  {
    "City": "Norton",
    "Zip Codes": [
      67654
    ]
  },
  {
    "City": "Nortonville",
    "Zip Codes": [
      66060
    ]
  },
  {
    "City": "Norwich",
    "Zip Codes": [
      67118
    ]
  },
  {
    "City": "Oakley",
    "Zip Codes": [
      67748
    ]
  },
  {
    "City": "Oberlin",
    "Zip Codes": [
      67749
    ]
  },
  {
    "City": "Offerle",
    "Zip Codes": [
      67563
    ]
  },
  {
    "City": "Ogallah",
    "Zip Codes": [
      67656
    ]
  },
  {
    "City": "Ogden",
    "Zip Codes": [
      66517
    ]
  },
  {
    "City": "Oketo",
    "Zip Codes": [
      66518
    ]
  },
  {
    "City": "Olathe",
    "Zip Codes": [
      66061,
      66062
    ]
  },
  {
    "City": "Olmitz",
    "Zip Codes": [
      67564
    ]
  },
  {
    "City": "Olpe",
    "Zip Codes": [
      66865
    ]
  },
  {
    "City": "Olsburg",
    "Zip Codes": [
      66520
    ]
  },
  {
    "City": "Onaga",
    "Zip Codes": [
      66521
    ]
  },
  {
    "City": "Oneida",
    "Zip Codes": [
      66522
    ]
  },
  {
    "City": "Opolis",
    "Zip Codes": [
      66760
    ]
  },
  {
    "City": "Osage City",
    "Zip Codes": [
      66523
    ]
  },
  {
    "City": "Osawatomie",
    "Zip Codes": [
      66064
    ]
  },
  {
    "City": "Osborne",
    "Zip Codes": [
      67473
    ]
  },
  {
    "City": "Oskaloosa",
    "Zip Codes": [
      66066
    ]
  },
  {
    "City": "Oswego",
    "Zip Codes": [
      67356
    ]
  },
  {
    "City": "Otis",
    "Zip Codes": [
      67565
    ]
  },
  {
    "City": "Ottawa",
    "Zip Codes": [
      66067
    ]
  },
  {
    "City": "Overbrook",
    "Zip Codes": [
      66524
    ]
  },
  {
    "City": "Overland Park",
    "Zip Codes": [
      66213,
      66214,
      66224,
      66207,
      66212,
      66204,
      66221,
      66223,
      66210
    ]
  },
  {
    "City": "Oxford",
    "Zip Codes": [
      67119
    ]
  },
  {
    "City": "Ozawkie",
    "Zip Codes": [
      66070
    ]
  },
  {
    "City": "Palco",
    "Zip Codes": [
      67657
    ]
  },
  {
    "City": "Palmer",
    "Zip Codes": [
      66962
    ]
  },
  {
    "City": "Paola",
    "Zip Codes": [
      66071
    ]
  },
  {
    "City": "Paradise",
    "Zip Codes": [
      67658
    ]
  },
  {
    "City": "Park",
    "Zip Codes": [
      67751
    ]
  },
  {
    "City": "Parker",
    "Zip Codes": [
      66072
    ]
  },
  {
    "City": "Parsons",
    "Zip Codes": [
      67357
    ]
  },
  {
    "City": "Partridge",
    "Zip Codes": [
      67566
    ]
  },
  {
    "City": "Pawnee Rock",
    "Zip Codes": [
      67567
    ]
  },
  {
    "City": "Paxico",
    "Zip Codes": [
      66526
    ]
  },
  {
    "City": "Peabody",
    "Zip Codes": [
      66866
    ]
  },
  {
    "City": "Peck",
    "Zip Codes": [
      67120
    ]
  },
  {
    "City": "Penokee",
    "Zip Codes": [
      67659
    ]
  },
  {
    "City": "Perry",
    "Zip Codes": [
      66073
    ]
  },
  {
    "City": "Peru",
    "Zip Codes": [
      67360
    ]
  },
  {
    "City": "Pfeifer",
    "Zip Codes": [
      67660
    ]
  },
  {
    "City": "Phillipsburg",
    "Zip Codes": [
      67661
    ]
  },
  {
    "City": "Piedmont",
    "Zip Codes": [
      67122
    ]
  },
  {
    "City": "Pierceville",
    "Zip Codes": [
      67868
    ]
  },
  {
    "City": "Piqua",
    "Zip Codes": [
      66761
    ]
  },
  {
    "City": "Pittsburg",
    "Zip Codes": [
      66762
    ]
  },
  {
    "City": "Plains",
    "Zip Codes": [
      67869
    ]
  },
  {
    "City": "Plainville",
    "Zip Codes": [
      67663
    ]
  },
  {
    "City": "Pleasanton",
    "Zip Codes": [
      66075
    ]
  },
  {
    "City": "Plevna",
    "Zip Codes": [
      67568
    ]
  },
  {
    "City": "Pomona",
    "Zip Codes": [
      66076
    ]
  },
  {
    "City": "Portis",
    "Zip Codes": [
      67474
    ]
  },
  {
    "City": "Potwin",
    "Zip Codes": [
      67123
    ]
  },
  {
    "City": "Powhattan",
    "Zip Codes": [
      66527
    ]
  },
  {
    "City": "Prairie View",
    "Zip Codes": [
      67664
    ]
  },
  {
    "City": "Prairie Village",
    "Zip Codes": [
      66208
    ]
  },
  {
    "City": "Pratt",
    "Zip Codes": [
      67124
    ]
  },
  {
    "City": "Prescott",
    "Zip Codes": [
      66767
    ]
  },
  {
    "City": "Pretty Prairie",
    "Zip Codes": [
      67570
    ]
  },
  {
    "City": "Princeton",
    "Zip Codes": [
      66078
    ]
  },
  {
    "City": "Protection",
    "Zip Codes": [
      67127
    ]
  },
  {
    "City": "Quenemo",
    "Zip Codes": [
      66528
    ]
  },
  {
    "City": "Quinter",
    "Zip Codes": [
      67752
    ]
  },
  {
    "City": "Ramona",
    "Zip Codes": [
      67475
    ]
  },
  {
    "City": "Randall",
    "Zip Codes": [
      66963
    ]
  },
  {
    "City": "Randolph",
    "Zip Codes": [
      66554
    ]
  },
  {
    "City": "Ransom",
    "Zip Codes": [
      67572
    ]
  },
  {
    "City": "Rantoul",
    "Zip Codes": [
      66079
    ]
  },
  {
    "City": "Raymond",
    "Zip Codes": [
      67573
    ]
  },
  {
    "City": "Reading",
    "Zip Codes": [
      66868
    ]
  },
  {
    "City": "Redfield",
    "Zip Codes": [
      66769
    ]
  },
  {
    "City": "Republic",
    "Zip Codes": [
      66964
    ]
  },
  {
    "City": "Rexford",
    "Zip Codes": [
      67753
    ]
  },
  {
    "City": "Richfield",
    "Zip Codes": [
      67953
    ]
  },
  {
    "City": "Richmond",
    "Zip Codes": [
      66080
    ]
  },
  {
    "City": "Riley",
    "Zip Codes": [
      66531
    ]
  },
  {
    "City": "Riverton",
    "Zip Codes": [
      66770
    ]
  },
  {
    "City": "Robinson",
    "Zip Codes": [
      66532
    ]
  },
  {
    "City": "Rock",
    "Zip Codes": [
      67131
    ]
  },
  {
    "City": "Rolla",
    "Zip Codes": [
      67954
    ]
  },
  {
    "City": "Rosalia",
    "Zip Codes": [
      67132
    ]
  },
  {
    "City": "Rose Hill",
    "Zip Codes": [
      67133
    ]
  },
  {
    "City": "Rossville",
    "Zip Codes": [
      66533
    ]
  },
  {
    "City": "Rozel",
    "Zip Codes": [
      67574
    ]
  },
  {
    "City": "Rush Center",
    "Zip Codes": [
      67575
    ]
  },
  {
    "City": "Russell",
    "Zip Codes": [
      67665
    ]
  },
  {
    "City": "Sabetha",
    "Zip Codes": [
      66534
    ]
  },
  {
    "City": "Saint Francis",
    "Zip Codes": [
      67756
    ]
  },
  {
    "City": "Saint George",
    "Zip Codes": [
      66535
    ]
  },
  {
    "City": "Saint Marys",
    "Zip Codes": [
      66536
    ]
  },
  {
    "City": "Saint Paul",
    "Zip Codes": [
      66771
    ]
  },
  {
    "City": "Salina",
    "Zip Codes": [
      67401
    ]
  },
  {
    "City": "Satanta",
    "Zip Codes": [
      67870
    ]
  },
  {
    "City": "Savonburg",
    "Zip Codes": [
      66772
    ]
  },
  {
    "City": "Sawyer",
    "Zip Codes": [
      67134
    ]
  },
  {
    "City": "Scammon",
    "Zip Codes": [
      66773
    ]
  },
  {
    "City": "Scandia",
    "Zip Codes": [
      66966
    ]
  },
  {
    "City": "Schoenchen",
    "Zip Codes": [
      67667
    ]
  },
  {
    "City": "Scott City",
    "Zip Codes": [
      67871
    ]
  },
  {
    "City": "Scranton",
    "Zip Codes": [
      66537
    ]
  },
  {
    "City": "Sedan",
    "Zip Codes": [
      67361
    ]
  },
  {
    "City": "Sedgwick",
    "Zip Codes": [
      67135
    ]
  },
  {
    "City": "Selden",
    "Zip Codes": [
      67757
    ]
  },
  {
    "City": "Seneca",
    "Zip Codes": [
      66538
    ]
  },
  {
    "City": "Severy",
    "Zip Codes": [
      67137
    ]
  },
  {
    "City": "Sharon",
    "Zip Codes": [
      67138
    ]
  },
  {
    "City": "Sharon Springs",
    "Zip Codes": [
      67758
    ]
  },
  {
    "City": "Shawnee",
    "Zip Codes": [
      66226,
      66216,
      66203,
      66217,
      66218
    ]
  },
  {
    "City": "Silver Lake",
    "Zip Codes": [
      66539
    ]
  },
  {
    "City": "Simpson",
    "Zip Codes": [
      67478
    ]
  },
  {
    "City": "Smith Center",
    "Zip Codes": [
      66967
    ]
  },
  {
    "City": "Soldier",
    "Zip Codes": [
      66540
    ]
  },
  {
    "City": "Solomon",
    "Zip Codes": [
      67480
    ]
  },
  {
    "City": "South Haven",
    "Zip Codes": [
      67140
    ]
  },
  {
    "City": "South Hutchinson",
    "Zip Codes": [
      67505
    ]
  },
  {
    "City": "Spearville",
    "Zip Codes": [
      67876
    ]
  },
  {
    "City": "Spivey",
    "Zip Codes": [
      67142
    ]
  },
  {
    "City": "Spring Hill",
    "Zip Codes": [
      66083
    ]
  },
  {
    "City": "St John",
    "Zip Codes": [
      67576
    ]
  },
  {
    "City": "Stafford",
    "Zip Codes": [
      67578
    ]
  },
  {
    "City": "Stark",
    "Zip Codes": [
      66775
    ]
  },
  {
    "City": "Sterling",
    "Zip Codes": [
      67579
    ]
  },
  {
    "City": "Stilwell",
    "Zip Codes": [
      66085
    ]
  },
  {
    "City": "Stockton",
    "Zip Codes": [
      67669
    ]
  },
  {
    "City": "Strong City",
    "Zip Codes": [
      66869
    ]
  },
  {
    "City": "Sublette",
    "Zip Codes": [
      67877
    ]
  },
  {
    "City": "Summerfield",
    "Zip Codes": [
      66541
    ]
  },
  {
    "City": "Sun City",
    "Zip Codes": [
      67143
    ]
  },
  {
    "City": "Sycamore",
    "Zip Codes": [
      67363
    ]
  },
  {
    "City": "Sylvan Grove",
    "Zip Codes": [
      67481
    ]
  },
  {
    "City": "Sylvia",
    "Zip Codes": [
      67581
    ]
  },
  {
    "City": "Syracuse",
    "Zip Codes": [
      67878
    ]
  },
  {
    "City": "Talmage",
    "Zip Codes": [
      67482
    ]
  },
  {
    "City": "Tampa",
    "Zip Codes": [
      67483
    ]
  },
  {
    "City": "Tecumseh",
    "Zip Codes": [
      66542
    ]
  },
  {
    "City": "Tescott",
    "Zip Codes": [
      67484
    ]
  },
  {
    "City": "Thayer",
    "Zip Codes": [
      66776
    ]
  },
  {
    "City": "Tipton",
    "Zip Codes": [
      67485
    ]
  },
  {
    "City": "Tonganoxie",
    "Zip Codes": [
      66086
    ]
  },
  {
    "City": "Topeka",
    "Zip Codes": [
      66619,
      66611,
      66612,
      66608,
      66609,
      66622,
      66603,
      66615,
      66616,
      66621,
      66607,
      66617,
      66604,
      66610,
      66606,
      66605,
      66614,
      66618
    ]
  },
  {
    "City": "Toronto",
    "Zip Codes": [
      66777
    ]
  },
  {
    "City": "Towanda",
    "Zip Codes": [
      67144
    ]
  },
  {
    "City": "Treece",
    "Zip Codes": [
      66778
    ]
  },
  {
    "City": "Tribune",
    "Zip Codes": [
      67879
    ]
  },
  {
    "City": "Troy",
    "Zip Codes": [
      66087
    ]
  },
  {
    "City": "Turon",
    "Zip Codes": [
      67583
    ]
  },
  {
    "City": "Tyro",
    "Zip Codes": [
      67364
    ]
  },
  {
    "City": "Udall",
    "Zip Codes": [
      67146
    ]
  },
  {
    "City": "Ulysses",
    "Zip Codes": [
      67880
    ]
  },
  {
    "City": "Uniontown",
    "Zip Codes": [
      66779
    ]
  },
  {
    "City": "Utica",
    "Zip Codes": [
      67584
    ]
  },
  {
    "City": "Valley Center",
    "Zip Codes": [
      67147
    ]
  },
  {
    "City": "Valley Falls",
    "Zip Codes": [
      66088
    ]
  },
  {
    "City": "Vassar",
    "Zip Codes": [
      66543
    ]
  },
  {
    "City": "Vermillion",
    "Zip Codes": [
      66544
    ]
  },
  {
    "City": "Victoria",
    "Zip Codes": [
      67671
    ]
  },
  {
    "City": "Viola",
    "Zip Codes": [
      67149
    ]
  },
  {
    "City": "Virgil",
    "Zip Codes": [
      66870
    ]
  },
  {
    "City": "Wakarusa",
    "Zip Codes": [
      66546
    ]
  },
  {
    "City": "Wakeeney",
    "Zip Codes": [
      67672
    ]
  },
  {
    "City": "Wakefield",
    "Zip Codes": [
      67487
    ]
  },
  {
    "City": "Waldo",
    "Zip Codes": [
      67673
    ]
  },
  {
    "City": "Waldron",
    "Zip Codes": [
      67150
    ]
  },
  {
    "City": "Walker",
    "Zip Codes": [
      67674
    ]
  },
  {
    "City": "Wallace",
    "Zip Codes": [
      67761
    ]
  },
  {
    "City": "Walnut",
    "Zip Codes": [
      66780
    ]
  },
  {
    "City": "Walton",
    "Zip Codes": [
      67151
    ]
  },
  {
    "City": "Wamego",
    "Zip Codes": [
      66547
    ]
  },
  {
    "City": "Washington",
    "Zip Codes": [
      66968
    ]
  },
  {
    "City": "Waterville",
    "Zip Codes": [
      66548
    ]
  },
  {
    "City": "Wathena",
    "Zip Codes": [
      66090
    ]
  },
  {
    "City": "Waverly",
    "Zip Codes": [
      66871
    ]
  },
  {
    "City": "Webber",
    "Zip Codes": [
      66970
    ]
  },
  {
    "City": "Weir",
    "Zip Codes": [
      66781
    ]
  },
  {
    "City": "Welda",
    "Zip Codes": [
      66091
    ]
  },
  {
    "City": "Wellington",
    "Zip Codes": [
      67152
    ]
  },
  {
    "City": "Wellsville",
    "Zip Codes": [
      66092
    ]
  },
  {
    "City": "Weskan",
    "Zip Codes": [
      67762
    ]
  },
  {
    "City": "West Mineral",
    "Zip Codes": [
      66782
    ]
  },
  {
    "City": "Westmoreland",
    "Zip Codes": [
      66549
    ]
  },
  {
    "City": "Westphalia",
    "Zip Codes": [
      66093
    ]
  },
  {
    "City": "Wetmore",
    "Zip Codes": [
      66550
    ]
  },
  {
    "City": "White City",
    "Zip Codes": [
      66872
    ]
  },
  {
    "City": "White Cloud",
    "Zip Codes": [
      66094
    ]
  },
  {
    "City": "Whitewater",
    "Zip Codes": [
      67154
    ]
  },
  {
    "City": "Whiting",
    "Zip Codes": [
      66552
    ]
  },
  {
    "City": "Wichita",
    "Zip Codes": [
      67235,
      67208,
      67219,
      67223,
      67227,
      67214,
      67210,
      67217,
      67212,
      67205,
      67228,
      67202,
      67215,
      67230,
      67213,
      67204,
      67226,
      67211,
      67216,
      67209,
      67218,
      67232,
      67203,
      67206,
      67260,
      67207,
      67220
    ]
  },
  {
    "City": "Williamsburg",
    "Zip Codes": [
      66095
    ]
  },
  {
    "City": "Wilmore",
    "Zip Codes": [
      67155
    ]
  },
  {
    "City": "Wilsey",
    "Zip Codes": [
      66873
    ]
  },
  {
    "City": "Wilson",
    "Zip Codes": [
      67490
    ]
  },
  {
    "City": "Winchester",
    "Zip Codes": [
      66097
    ]
  },
  {
    "City": "Windom",
    "Zip Codes": [
      67491
    ]
  },
  {
    "City": "Winfield",
    "Zip Codes": [
      67156
    ]
  },
  {
    "City": "Winona",
    "Zip Codes": [
      67764
    ]
  },
  {
    "City": "Woodbine",
    "Zip Codes": [
      67492
    ]
  },
  {
    "City": "Woodston",
    "Zip Codes": [
      67675
    ]
  },
  {
    "City": "Wright",
    "Zip Codes": [
      67882
    ]
  },
  {
    "City": "Yates Center",
    "Zip Codes": [
      66783
    ]
  },
  {
    "City": "Zenda",
    "Zip Codes": [
      67159
    ]
  }
]